[
    {
        "id": "simple-connector",
        "name": "Connector",
        "description": "Lorem ipsum dolor sit amet, consectetur adipiscing elit, sed do eiusmod tempor incididunt ut labore et dolore magna aliqua.",
        "svgViewBox": "0 0 100 20",
        "config": []
    },
    {
        "id": "empty-subcircuit",
        "name": "Empty Subcircuit",
        "description": "Lorem ipsum dolor sit amet, consectetur adipiscing elit, sed do eiusmod tempor incididunt ut labore et dolore magna aliqua.",
        "svgViewBox": "0 0 80 80",
        "config": []
    }
]